{
  "url": "https://apps.apple.com/cn/app/id1470343227",
  "id": "id1470343227",
  "app_name": "\u5fae\u5546\u8f93\u5165\u6cd5-\u670b\u53cb\u5708\u4e0d\u6298\u53e0\u8f93\u5165\u6cd5",
  "rank_desc": "",
  "rating_desc": "4.9\uff0c638 \u4e2a\u8bc4\u5206",
  "info_list": {
    "Seller": "",
    "Size": "",
    "Copyright": "\u00a9 Shujuan Wang",
    "\u4f9b\u5e94\u5546": "Shujuan Wang",
    "\u5927\u5c0f": "23.1 MB",
    "\u5e74\u9f84\u5206\u7ea7": "\u96504\u5c81\u4ee5\u4e0a",
    "\u4ef7\u683c": "\u514d\u8d39"
  },
  "version_history": []
}